{
    "parent": "minecraft:item/handheld",
    "loader": "neoforge:separate_transforms",
    "base": {
        "parent": "discerning_the_eldritch:item/tempestuous_tome_model"
    },
    "perspectives": {
        "gui": {
            "parent": "discerning_the_eldritch:item/tempestuous_tome_gui"
        },
        "head": {
            "textures": {
                "book": "discerning_the_eldritch:item/spell_books/tempestuous_tome_open",
                "particle": "discerning_the_eldritch:item/spell_books/tempestuous_tome_open"
            },
            "parent": "irons_spellbooks:item/template_spell_book_model_open"
        }
    }
}